baselines/__init__.py
baselines/softimpute.py
baselines/usvt.py
nsquared/__init__.py
nsquared/data_types.py
nsquared/dr_nn.py
nsquared/estimation_methods.py
nsquared/fit_methods.py
nsquared/nadaraya_watson.py
nsquared/nnimputer.py
nsquared/star_nn.py
nsquared/ts_nn.py
nsquared/vanilla_nn.py
nsquared/datasets/__init__.py
nsquared/datasets/dataloader_base.py
nsquared/datasets/dataloader_factory.py
nsquared/datasets/earnings/__init__.py
nsquared/datasets/earnings/loader.py
nsquared/datasets/heartsteps/__init__.py
nsquared/datasets/heartsteps/loader.py
nsquared/datasets/movielens/__init__.py
nsquared/datasets/movielens/loader.py
nsquared/datasets/prompteval/__init__.py
nsquared/datasets/prompteval/loader.py
nsquared/datasets/prop99/__init__.py
nsquared/datasets/prop99/loader.py
nsquared/datasets/synthetic_data/__init__.py
nsquared/datasets/synthetic_data/loader.py
nsquared/simulations/__init__.py
nsquared/simulations/mcar.py
nsquared/simulations/mnar.py
nsquared/utils/__init__.py
nsquared/utils/experiments.py
nsquared/utils/helper_fns.py
nsquared/utils/kernels.py
nsquared/utils/plotting_utils.py
nsquared-1.0.0.dist-info/licenses/LICENSE
nsquared-1.0.0.dist-info/METADATA
nsquared-1.0.0.dist-info/WHEEL
nsquared-1.0.0.dist-info/top_level.txt
nsquared-1.0.0.dist-info/RECORD
