Metadata-Version: 2.4
Name: nsquared
Version: 1.0.0
Summary: A comprehensive nearest neighbors library for matrix completion with scalar and distributional entries
Author-email: Aashish Khubchandani <akk223@cornell.edu>, Albert Gong <agong@cs.cornell.edu>, Caleb Chin <ctc92@cornell.edu>, Harshvardan Maskara <hm475@cornell.edu>, Jacob Feitelberg <jef2182@columbia.edu>, Kyuseong Choi <kc728@cornell.edu>, Manit Paul <paulman@wharton.upenn.edu>, Raaz Dwivedi <dwivedi@cornell.edu>, Tathagata Sadhukhan <ts767@cornell.edu>
License-Expression: MIT
Project-URL: Homepage, https://github.com/aashish-khub/NearestNeighbors
Project-URL: Documentation, https://github.com/aashish-khub/NearestNeighbors/blob/main/README.md
Project-URL: Repository, https://github.com/aashish-khub/NearestNeighbors.git
Project-URL: Issues, https://github.com/aashish-khub/NearestNeighbors/issues
Keywords: machine learning,matrix completion,nearest neighbors,imputation,causal inference
Classifier: Development Status :: 4 - Beta
Classifier: Intended Audience :: Science/Research
Classifier: Intended Audience :: Developers
Classifier: Operating System :: OS Independent
Classifier: Programming Language :: Python :: 3
Classifier: Programming Language :: Python :: 3.10
Classifier: Programming Language :: Python :: 3.11
Classifier: Programming Language :: Python :: 3.12
Classifier: Topic :: Scientific/Engineering :: Artificial Intelligence
Classifier: Topic :: Scientific/Engineering :: Mathematics
Classifier: Topic :: Software Development :: Libraries :: Python Modules
Requires-Python: >=3.10
License-File: LICENSE
Requires-Dist: numpy
Requires-Dist: pandas
Requires-Dist: matplotlib
Requires-Dist: hyperopt
Requires-Dist: joblib
Requires-Dist: requests
Requires-Dist: seaborn
Requires-Dist: SyntheticControlMethods
Requires-Dist: fancyimpute
Requires-Dist: datasets
Requires-Dist: tabulate
Requires-Dist: tqdm
Requires-Dist: wrds
Provides-Extra: dev
Requires-Dist: pre-commit; extra == "dev"
Requires-Dist: ruff; extra == "dev"
Requires-Dist: pytest; extra == "dev"
Dynamic: license-file
